CHANGELOG.md
LICENSE
discord/ext/lava/__init__.py
discord/ext/lava/exceptions.py
discord/ext/lava/node.py
discord/ext/lava/objects/__init__.py
discord/ext/lava/objects/collection.py
discord/ext/lava/objects/enums.py
discord/ext/lava/objects/events.py
discord/ext/lava/objects/filters/__init__.py
discord/ext/lava/objects/filters/channel_mix.py
discord/ext/lava/objects/filters/distortion.py
discord/ext/lava/objects/filters/equalizer.py
discord/ext/lava/objects/filters/filter.py
discord/ext/lava/objects/filters/karaoke.py
discord/ext/lava/objects/filters/low_pass.py
discord/ext/lava/objects/filters/rotation.py
discord/ext/lava/objects/filters/timescale.py
discord/ext/lava/objects/filters/tremolo.py
discord/ext/lava/objects/filters/vibrato.py
discord/ext/lava/objects/filters/volume.py
discord/ext/lava/objects/search.py
discord/ext/lava/objects/track.py
discord/ext/lava/player.py
discord/ext/lava/pool.py
discord/ext/lava/py.typed
discord/ext/lava/queue.py
discord/ext/lava/types.py
discord/ext/lava/utils.py
discord_ext_lava-0.5.0.dist-info/LICENSE
discord_ext_lava-0.5.0.dist-info/WHEEL
discord_ext_lava-0.5.0.dist-info/METADATA
discord_ext_lava-0.5.0.dist-info/RECORD
